<?xml version="1.0" encoding="UTF-8"?>
<document name="collectionobjects">
  <ns2:collectionspace_core xmlns:ns2="http://collectionspace.org/collectionspace_core/" xmlns:xsi="http://www.w3.org/2001/XMLSchema-instance">
    <createdAt>2020-02-04T23:23:17.382Z</createdAt>
    <updatedBy>admin@cspace.ohiohistory.org</updatedBy>
    <createdBy>admin@cspace.ohiohistory.org</createdBy>
    <workflowState>project</workflowState>
    <tenantId>1885</tenantId>
    <refName>urn:cspace:cspace.ohiohistory.org:collectionobjects:id(418d0a41-d98b-4681-9503)'20CS.001.0005'</refName>
    <uri>/collectionobjects/418d0a41-d98b-4681-9503</uri>
    <updatedAt>2020-02-04T23:23:17.382Z</updatedAt>
  </ns2:collectionspace_core>
  <ns2:collectionobjects_common xmlns:ns2="http://collectionspace.org/services/collectionobject" xmlns:xsi="http://www.w3.org/2001/XMLSchema-instance">
    <fieldCollectionDateGroup>
      <scalarValuesComputed/>
      <dateEarliestSingleCertainty/>
      <dateEarliestSingleQualifierUnit/>
      <dateDisplayDate/>
      <dateLatestScalarValue/>
      <dateEarliestSingleQualifierValue/>
      <datePeriod/>
      <dateLatestEra/>
      <dateEarliestSingleDay/>
      <dateEarliestSingleQualifier/>
      <dateEarliestSingleYear/>
      <dateLatestCertainty/>
      <dateAssociation/>
      <dateLatestDay/>
      <dateEarliestSingleMonth/>
      <dateEarliestSingleEra/>
      <dateLatestYear/>
      <dateLatestQualifierUnit/>
      <dateNote/>
      <dateLatestQualifierValue/>
      <dateLatestQualifier/>
      <dateEarliestScalarValue/>
      <dateLatestMonth/>
    </fieldCollectionDateGroup>
    <owners/>
    <fieldCollectionMethods/>
    <contentActivities/>
    <objectProductionDateGroupList/>
    <contentConcepts/>
    <assocEventPlaces/>
    <assocActivityGroupList/>
    <objectProductionReasons/>
    <assocPlaceGroupList/>
    <objectNameList/>
    <styles/>
    <materialGroupList/>
    <assocObjectGroupList/>
    <fieldCollectors/>
    <responsibleDepartments/>
    <textualInscriptionGroupList/>
    <objectNumber>20CS.001.0005</objectNumber>
    <fieldColEventNames/>
    <colors/>
    <contentScripts/>
    <objectProductionPlaceGroupList/>
    <referenceGroupList/>
    <assocDateGroupList/>
    <briefDescriptions/>
    <contentLanguages/>
    <recordStatus>new</recordStatus>
    <assocPersonGroupList/>
    <titleGroupList/>
    <assocConceptGroupList/>
    <usageGroupList/>
    <assocCulturalContextGroupList/>
    <otherNumberList/>
    <objectProductionPeopleGroupList/>
    <assocPeopleGroupList/>
    <assocEventOrganizations/>
    <contentPeoples/>
    <measuredPartGroupList/>
    <contentObjectGroupList/>
    <ownershipDateGroupList/>
    <technicalAttributeGroupList/>
    <nonTextualInscriptionGroupList/>
    <assocEventPersons/>
    <objectProductionPersonGroupList/>
    <contentPersons/>
    <fieldCollectionSources/>
    <contentEventNameGroupList/>
    <ownersReferences/>
    <viewersReferences/>
    <objectProductionOrganizationGroupList/>
    <publishToList>
      <publishTo>urn:cspace:core.collectionspace.org:vocabularies:name(publishto):item:name(none)'None'</publishTo>
    </publishToList>
    <assocOrganizationGroupList/>
    <contentOrganizations/>
    <contentPlaces/>
    <contentOtherGroupList/>
    <contentDateGroup>
      <scalarValuesComputed/>
      <dateEarliestSingleCertainty/>
      <dateEarliestSingleQualifierUnit/>
      <dateDisplayDate/>
      <dateLatestScalarValue/>
      <dateEarliestSingleQualifierValue/>
      <datePeriod/>
      <dateLatestEra/>
      <dateEarliestSingleDay/>
      <dateEarliestSingleQualifier/>
      <dateEarliestSingleYear/>
      <dateLatestCertainty/>
      <dateAssociation/>
      <dateLatestDay/>
      <dateEarliestSingleMonth/>
      <dateEarliestSingleEra/>
      <dateLatestYear/>
      <dateLatestQualifierUnit/>
      <dateNote/>
      <dateLatestQualifierValue/>
      <dateLatestQualifier/>
      <dateEarliestScalarValue/>
      <dateLatestMonth/>
    </contentDateGroup>
    <objectStatusList/>
    <objectComponentGroupList/>
    <comments/>
    <assocEventPeoples/>
    <techniqueGroupList/>
    <inventoryStatusList>
      <inventoryStatus>urn:cspace:core.collectionspace.org:vocabularies:name(inventorystatus):item:name(unknown)'unknown'</inventoryStatus>
    </inventoryStatusList>
    <contentPositions/>
    <forms/>
  </ns2:collectionobjects_common>
  <ns2:collectionobjects_culturalcare xmlns:ns2="http://collectionspace.org/services/collectionobject/domain/collectionobject" xmlns:xsi="http://www.w3.org/2001/XMLSchema-instance">
    <accessLimitationsGroupList/>
    <culturalCareNotes/>
  </ns2:collectionobjects_culturalcare>
  <ns2:collectionobjects_ohc xmlns:ns2="http://collectionspace.org/services/collectionobject/domain/ohc" xmlns:xsi="http://www.w3.org/2001/XMLSchema-instance">
    <namedTimePeriods/>
    <categoryGroupList/>
    <oaiSiteGroupList/>
    <apparelSizes/>
  </ns2:collectionobjects_ohc>
  <ns2:collectionobjects_annotation xmlns:ns2="http://collectionspace.org/services/collectionobject/domain/annotation" xmlns:xsi="http://www.w3.org/2001/XMLSchema-instance">
    <annotationGroupList/>
  </ns2:collectionobjects_annotation>
  <ns2:collectionobjects_nagpra xmlns:ns2="http://collectionspace.org/services/collectionobject/domain/nagpra" xmlns:xsi="http://www.w3.org/2001/XMLSchema-instance">
    <nagpraReportFiledDate>
      <scalarValuesComputed/>
      <dateEarliestSingleCertainty/>
      <dateEarliestSingleQualifierUnit/>
      <dateDisplayDate/>
      <dateLatestScalarValue/>
      <dateEarliestSingleQualifierValue/>
      <datePeriod/>
      <dateLatestEra/>
      <dateEarliestSingleDay/>
      <dateEarliestSingleQualifier/>
      <dateEarliestSingleYear/>
      <dateLatestCertainty/>
      <dateAssociation/>
      <dateLatestDay/>
      <dateEarliestSingleMonth/>
      <dateEarliestSingleEra/>
      <dateLatestYear/>
      <dateLatestQualifierUnit/>
      <dateNote/>
      <dateLatestQualifierValue/>
      <dateLatestQualifier/>
      <dateEarliestScalarValue/>
      <dateLatestMonth/>
    </nagpraReportFiledDate>
    <nagpraReportFiled>false</nagpraReportFiled>
    <graveAssocCodes/>
    <repatriationNotes/>
    <nagpraCategories/>
    <nagpraCulturalDeterminations/>
    <nagpraInventoryNames/>
  </ns2:collectionobjects_nagpra>
  <ns2:collectionobjects_anthro xmlns:ns2="http://collectionspace.org/services/collectionobject/domain/anthro" xmlns:xsi="http://www.w3.org/2001/XMLSchema-instance">
    <ethnoFileCodes/>
    <localityGroupList/>
    <commingledRemainsGroupList/>
    <anthroOwnershipGroupList/>
  </ns2:collectionobjects_anthro>
  <ns2:collectionobjects_naturalhistory_extension xmlns:ns2="http://collectionspace.org/services/collectionobject/domain/naturalhistory_extension" xmlns:xsi="http://www.w3.org/2001/XMLSchema-instance">
    <associatedTaxaGroupList/>
    <determinationHistoryGroupList/>
    <taxonomicIdentGroupList/>
    <localityGroupList/>
    <typeSpecimenGroupList/>
  </ns2:collectionobjects_naturalhistory_extension>
  <ns2:account_permission xmlns:ns2="http://collectionspace.org/services/authorization">
    <account>
      <accountId>771a6647-d10b-4857-8637-b5b978ffaf5a</accountId>
      <screenName>Converter Tool</screenName>
      <userId>converter@lyrasistechnology.org</userId>
      <tenantId>1885</tenantId>
    </account>
  </ns2:account_permission>
</document>
